htmx_components_flask/__init__.py
htmx_components_flask/templates/htmx_components_flask/gridview.html
htmx_components_flask/templates/htmx_components_flask/pager.html
htmx_components_flask/templates/htmx_components_flask/sortlink.html
htmx_components_flask/templates/htmx_components_flask/treeview.html
htmx_components_flask/templates/htmx_components_flask/form/description.html
htmx_components_flask/templates/htmx_components_flask/form/errors.html
htmx_components_flask/templates/htmx_components_flask/form/horizontal.html
htmx_components_flask-0.0.2.dist-info/LICENSE
htmx_components_flask-0.0.2.dist-info/METADATA
htmx_components_flask-0.0.2.dist-info/WHEEL
htmx_components_flask-0.0.2.dist-info/top_level.txt
htmx_components_flask-0.0.2.dist-info/RECORD
