Metadata-Version: 2.1
Name: htmx-components-flask
Version: 0.0.2
Summary: HTMX Components for Flask
Author: Neil McGuigan
Project-URL: Homepage, https://github.com/neilmcguigan/htmx-components-flask
License-File: LICENSE
Requires-Dist: flask (>=2.0)
Requires-Dist: lxml (==4.9.3)
Requires-Dist: htmx-components-python
